{
  "text": "Muchísimas gracias, señor Presidente.  Buen día con todos.  Un saludo a mi provincia de Ríos, al país entero,  a través de estos medios de comunicación legislativos.  Mi saludo respetuoso al pueblo ecuatoriano y de manera especial  a los hombres y mujeres de nuestras Fuerzas Armadas,  al personal del servicio activo, a los pensionistas, a las viudas,  a los huérfanos y a la familia militar.  Hoy no estamos debatiendo únicamente un articulado de casi 500 páginas.  Hoy estamos decidiendo de qué lado de la historia queremos estar.  Del lado de quienes, desde un escritorio,  pretenden resolver los problemas financieros del Estado  recortando los derechos o del lado de quienes,  con uniforme puesto, patrullan nuestras calles,  vigilan nuestras fronteras y enfrentan al crimen organizado,  poniendo en riesgo su vida.  Mientras nosotros debatimos aquí,  hay soldados de tropa, delegados en Quevedo,  en los ríos, en Esmeraldas, en Guayaquil,  en cada rincón de la patria.  Están lejos de sus hijos, de sus padres,  enfrentando bandas criminales cada vez más violentas  para devolverle la tranquilidad al Ecuador.  Y resulta profundamente injusto  que mientras ellos protegen nuestras familias,  desde este Parlamento,  podamos aprobar disposiciones  que generen incertidumbre  sobre su jubilación,  su cesantía  y el sustento económico de sus hogares.  No nos equivoquemos.  La sostenibilidad del sistema es necesaria,  por supuesto.  Nadie discute la importancia  de garantizar la estabilidad del IFA.  Pero la sostenibilidad  no puede convertirse en un pretexto  de trasladar el costo de la crisis  a quienes reciben menos ingresos.  No podemos aceptar reformas laborales  que se deciden en cuatro paredes  sin escuchar realmente a la tropa,  sin incorporar sus observaciones  y sin valorar la experiencia  de quienes conocen de primera mano  las dificultades que enfrenta  el militar ecuatoriano.  No podemos permitir medidas regresivas  que afecten los derechos adquiridos.  No podemos aceptar  que se modifiquen las reglas de juego  para quienes ingresaron al servicio  bajo determinadas condiciones  y construyeron su proyecto de vida  confiando en la palabra del Estado.  Tampoco podemos admitir  que se impongan nuevas cargas económicas  a soldados, a pensionistas y a viudas  que ya hacen enormes esfuerzos  para llegar a fin de mes.  Desde la Comisión del Derecho al Trabajo  y desde nuestra bancada  hemos demostrado que es posible  hacer política de otra manera.  No hemos venido a bloquear soluciones,  hemos venido a construir acuerdos.  Escuchamos a la tropa,  abrimos la puerta de estas asambleas  a sus representantes  y promovimos un diálogo técnico serio  entre la consultora encargada  del estudio actuarial  y los especialistas designados  por el personal militar.  Gracias a este trabajo  logramos consensos importantes.  Pusimos un esquema progresivo  para los aportes al seguro de salud.  Para quienes tienen menos ingresos  el aporte sea también menos  para sus pensiones  y de esta manera  que el costo de la canasta básica  tenga un tratamiento  para quienes ganan  menos de la canasta básica  tenga un tratamiento justo y solidario.  Planteamos también  mecanismos modernos  de permanencia voluntaria  en el servicio  mediante incentivos  que reconozcan la experiencia  y el compromiso  de nuestros militares  en lugar de imponer medidas punitivas  que generen incertidumbre  al soldado ecoturiano.  Compañeros legisladores,  la grandeza de un país  se mide en la manera  en que se trata  a quienes lo defienden.  No carguemos sobre los hombros  al soldado de la tropa  el peso de los errores administrativos  por la falta de planificación  o los desequilibrios financieros  acumulados por años.  Legiremos con responsabilidad  pero también con sensibilidad humana.  Cumplamos el mandato constitucional  de proteger derechos  y respetar el principio  de la no regresividad.  A la familia militar  quiero decirles con absoluta claridad  no están solos.  Seguiremos acompañando  sus demandas legítimas.  Seguiremos impulsando  propuestas visibles  y seguiremos levantando nuestra voz  cada vez que se pretenda  sacrificar  a quienes han sacrificado  por tanto el Ecuador.  Porque un país  que abandona a sus soldados  termina debilitando  su propia seguridad  y su propia democracia.  en ese sentido  a quienes  los jubilados  están fuera  de este  pleno de la asamblea  les decimos  pues que  estamos con ellos  y que vamos a seguir  respaldando  su demanda  para de esta manera  tener a un soldado  protegido  y una fuerza armada  digna para el pueblo ecuatoriano.  Muchísimas gracias.  Gracias asamblea.",
  "language": "es",
  "duration": 350.92,
  "speakers_detected": 1,
  "segments": [
    {
      "id": 0,
      "start": 3.79,
      "end": 350.96,
      "text": "Muchísimas gracias, señor Presidente.  Buen día con todos.  Un saludo a mi provincia de Ríos, al país entero,  a través de estos medios de comunicación legislativos.  Mi saludo respetuoso al pueblo ecuatoriano y de manera especial  a los hombres y mujeres de nuestras Fuerzas Armadas,  al personal del servicio activo, a los pensionistas, a las viudas,  a los huérfanos y a la familia militar.  Hoy no estamos debatiendo únicamente un articulado de casi 500 páginas.  Hoy estamos decidiendo de qué lado de la historia queremos estar.  Del lado de quienes, desde un escritorio,  pretenden resolver los problemas financieros del Estado  recortando los derechos o del lado de quienes,  con uniforme puesto, patrullan nuestras calles,  vigilan nuestras fronteras y enfrentan al crimen organizado,  poniendo en riesgo su vida.  Mientras nosotros debatimos aquí,  hay soldados de tropa, delegados en Quevedo,  en los ríos, en Esmeraldas, en Guayaquil,  en cada rincón de la patria.  Están lejos de sus hijos, de sus padres,  enfrentando bandas criminales cada vez más violentas  para devolverle la tranquilidad al Ecuador.  Y resulta profundamente injusto  que mientras ellos protegen nuestras familias,  desde este Parlamento,  podamos aprobar disposiciones  que generen incertidumbre  sobre su jubilación,  su cesantía  y el sustento económico de sus hogares.  No nos equivoquemos.  La sostenibilidad del sistema es necesaria,  por supuesto.  Nadie discute la importancia  de garantizar la estabilidad del IFA.  Pero la sostenibilidad  no puede convertirse en un pretexto  de trasladar el costo de la crisis  a quienes reciben menos ingresos.  No podemos aceptar reformas laborales  que se deciden en cuatro paredes  sin escuchar realmente a la tropa,  sin incorporar sus observaciones  y sin valorar la experiencia  de quienes conocen de primera mano  las dificultades que enfrenta  el militar ecuatoriano.  No podemos permitir medidas regresivas  que afecten los derechos adquiridos.  No podemos aceptar  que se modifiquen las reglas de juego  para quienes ingresaron al servicio  bajo determinadas condiciones  y construyeron su proyecto de vida  confiando en la palabra del Estado.  Tampoco podemos admitir  que se impongan nuevas cargas económicas  a soldados, a pensionistas y a viudas  que ya hacen enormes esfuerzos  para llegar a fin de mes.  Desde la Comisión del Derecho al Trabajo  y desde nuestra bancada  hemos demostrado que es posible  hacer política de otra manera.  No hemos venido a bloquear soluciones,  hemos venido a construir acuerdos.  Escuchamos a la tropa,  abrimos la puerta de estas asambleas  a sus representantes  y promovimos un diálogo técnico serio  entre la consultora encargada  del estudio actuarial  y los especialistas designados  por el personal militar.  Gracias a este trabajo  logramos consensos importantes.  Pusimos un esquema progresivo  para los aportes al seguro de salud.  Para quienes tienen menos ingresos  el aporte sea también menos  para sus pensiones  y de esta manera  que el costo de la canasta básica  tenga un tratamiento  para quienes ganan  menos de la canasta básica  tenga un tratamiento justo y solidario.  Planteamos también  mecanismos modernos  de permanencia voluntaria  en el servicio  mediante incentivos  que reconozcan la experiencia  y el compromiso  de nuestros militares  en lugar de imponer medidas punitivas  que generen incertidumbre  al soldado ecoturiano.  Compañeros legisladores,  la grandeza de un país  se mide en la manera  en que se trata  a quienes lo defienden.  No carguemos sobre los hombros  al soldado de la tropa  el peso de los errores administrativos  por la falta de planificación  o los desequilibrios financieros  acumulados por años.  Legiremos con responsabilidad  pero también con sensibilidad humana.  Cumplamos el mandato constitucional  de proteger derechos  y respetar el principio  de la no regresividad.  A la familia militar  quiero decirles con absoluta claridad  no están solos.  Seguiremos acompañando  sus demandas legítimas.  Seguiremos impulsando  propuestas visibles  y seguiremos levantando nuestra voz  cada vez que se pretenda  sacrificar  a quienes han sacrificado  por tanto el Ecuador.  Porque un país  que abandona a sus soldados  termina debilitando  su propia seguridad  y su propia democracia.  en ese sentido  a quienes  los jubilados  están fuera  de este  pleno de la asamblea  les decimos  pues que  estamos con ellos  y que vamos a seguir  respaldando  su demanda  para de esta manera  tener a un soldado  protegido  y una fuerza armada  digna para el pueblo ecuatoriano.  Muchísimas gracias.  Gracias asamblea.",
      "speaker_id": "speaker_0",
      "speaker": {
        "id": "speaker_0",
        "name": "Marcos Humberto Alvarado Espinel",
        "confidence": 0.75
      }
    }
  ],
  "video_id": "P_y8PoQ1pFE",
  "source": "local-pyannote-community-1+whisper-large-v3-turbo",
  "speaker_mapping": {
    "speaker_0": {
      "name": "Marcos Humberto Alvarado Espinel",
      "confidence": 0.75,
      "votes": {
        "[OOV] A Por Los": 1
      },
      "samples": 10,
      "successful_reads": 1,
      "source": "title"
    }
  },
  "title": "Asambleísta Humberto Alvarado - Sesión 103",
  "url": "https://www.youtube.com/watch?v=P_y8PoQ1pFE",
  "published_at": "2026-06-24T00:00:00Z",
  "channel_title": "Asamblea Nacional del Ecuador",
  "id": "P_y8PoQ1pFE",
  "date": "2026-06-24T00:00:00Z",
  "source_url": "https://www.youtube.com/watch?v=P_y8PoQ1pFE",
  "speaker_stats": [
    {
      "id": "speaker_0",
      "name": "Marcos Humberto Alvarado Espinel",
      "party": null,
      "province": null,
      "total_time": 347.17,
      "interventions": 1,
      "word_count": 690
    }
  ],
  "video_type": "clip"
}