{
  "text": "palabra el asambleísta Juan Andrés González.  Pueblo ecuatoriano, buenas tardes. Señora Presidenta, asambleístas presentes, medios  de comunicación. De cierta manera, yo celebro que traigan este tema al pleno de la Asamblea  Nacional, porque es la oportunidad perfecta para que el país entero vea cómo opera la  desesperación de un gobierno acorralado. La bancada de ADN nos pide hoy que hablemos de  cámaras de seguridad, de testimonios del señor Rangel, de teléfonos abiertos y de  supuestos espionajes. Han hecho un esfuerzo enorme por ponerle el nombre de Segura-EP a  este debate. ¿Y saben por qué? Porque les aterra llamarlo por su verdadero nombre, el  caso Porcho. Quieren que el Ecuador debata sobre cómo se obtuvo la información, para  que nadie hable de lo que demuestra esa información. ¿Cómo se obtuvo? Les ahorro el trabajo.  Con fecha 25 de septiembre del 25, el Comité de Derechos Humanos emitió un oficio a mi despacho  solicitando que en mi calidad de asambleísta solicite videos y trazabilidad a Segura-EP  en relación a las bombas que explotaron en la bahía de Guayaquil. Lo hice de inmediato.  El 26 de septiembre del 25 solicité la información y el 29 de septiembre recibí la información.  Es por eso que el 15 de octubre los expuse. ¿Y digo por qué? Porque denunciamos que luego  de la explosión en la bahía de Guayaquil se detecta que Iván Ballesteros, supuesto implicado  en la explosión en la bahía, va a su domicilio, al siguiente día lo detienen y cinco minutos  después al domicilio del detenido del implicado Ballesteros. Cinco minutos después llega un  Porsche Cayenne de placas GRY 3452 perteneciente a Industrial Molinera, que pertenece a la familia  Novo. ¿Por qué no se investiga eso? Está claro. Ya está de dónde se obtuvo la información.  Y pregunto ante este pleno, ¿por qué han volcado todo el aparataje del Estado en contra  de quienes fiscalizamos? ¿Por qué? La sombra constante, la amenaza, la filtración de testimonios  manipulados en fiscalía. La fiscalía en relación a Ports dijo que no se puede abrir el teléfono  del señor Ballesteros porque no les ha entregado la clave. Pero lo más cínico de esta narrativa  es el falso discurso sobre los recursos públicos. Hoy se rascan las vestiduras diciendo que se han usado  dinero del Estado para investigar. ¡Qué ironía! Revisen por favor quién pagó el PIB en el último partido  de Ecuador. Aquí no hay ningún espionaje ilegal contra ciudadanos ni ciudadanas. Lo que hay es un  gobierno a que se le descubrieron sus pactos bajo la mesa y ahora quieren criminalizar a quienes hacemos  nuestro trabajo de fiscalización. Tremendo. Mientras el país se quedaba a oscuras y perdíamos millones  de dólares. No pasaba nada. Como no pasa nada con el caso Progen y ATM. Un robo descarado que nadie dice nada.  Como no pasa nada, como no pasa nada con el caso Porsche. Si yo no investigo, si yo no investigo el caso Porsche,  entonces después les suela que sí, el silencio tora. Que si no investigo la explosión de la bomba, que si no investigo  el carro Porsche Cayet que llega ahí. Entonces no me estoy convirtiendo en cómplice. Después les suele que supuesto autoatentado.  Y no pasa nada con los niños de las Malvinas. Después les suele supuesto terrorismo.  Y investiguen. Entonces, díganle al pueblo ecuatoriano qué pasa con 2.3 toneladas de cocaína en Blástica.  ¿Qué pasa con incautación de cocaína en San Luis? ¿Qué pasa con 70 millones de desvanecidos del SRI?  ¿Qué pasa con Gala Medios y la compra de medios de comunicación que nadie sabe cómo?  ¿Qué está pasando?  Pero, ¿saben lo que sucede aquí?  Hay ocasiones donde a mí me gustaría responder los insultos que se me generan.  Pero, como dijo Tsun Tzu, uno elige los enemigos y yo elijo mis enemigos.  Y para responder, tienen que estar a la altura del conflicto.  Así que, ¿saben qué es lo que pasa?  Es que como están acorralados, como no quieren investigar lo que realmente tienen que investigar,  es la vieja táctica de la impunidad.  Cuando descubren al corrupto robando porque una cámara lo grabó,  su defensa es acusar a quien instaló la cámara por invasión a la privacidad.  Y no pasa absolutamente nada.  Ecuatorianas y ecuatorianos.  Yo he sido realmente una persona que ha dado la cara ante el pueblo ecuatoriano.  Señores del gobierno, abran los teléfonos que quieran.  Expongan los audios que quieran.  Presionen a los testigos que quieran.  Inventen las historias que necesiten.  La verdad ya está afuera.  El caso Progen, el caso Porche, el caso Blastig, el Galamé, ya están afuera.  Y el pueblo conoce de aquello.  Y eso no se va a borrar de la mente del pueblo ecuatoriano  porque ustedes persigan a quienes estamos fiscalizando.  Sigan usando el aparataje del Estado como su escudo personal.  Que nosotros seguiremos usando la fiscalización desde aquí  y la fuerza del pueblo ecuatoriano  como nuestra única arma y herramienta  para defender este país  que ya se cansó de ustedes.  Buena suerte.",
  "language": "es",
  "duration": 463.15,
  "speakers_detected": 1,
  "segments": [
    {
      "id": 0,
      "start": 0.03,
      "end": 458.32,
      "text": "palabra el asambleísta Juan Andrés González.  Pueblo ecuatoriano, buenas tardes. Señora Presidenta, asambleístas presentes, medios  de comunicación. De cierta manera, yo celebro que traigan este tema al pleno de la Asamblea  Nacional, porque es la oportunidad perfecta para que el país entero vea cómo opera la  desesperación de un gobierno acorralado. La bancada de ADN nos pide hoy que hablemos de  cámaras de seguridad, de testimonios del señor Rangel, de teléfonos abiertos y de  supuestos espionajes. Han hecho un esfuerzo enorme por ponerle el nombre de Segura-EP a  este debate. ¿Y saben por qué? Porque les aterra llamarlo por su verdadero nombre, el  caso Porcho. Quieren que el Ecuador debata sobre cómo se obtuvo la información, para  que nadie hable de lo que demuestra esa información. ¿Cómo se obtuvo? Les ahorro el trabajo.  Con fecha 25 de septiembre del 25, el Comité de Derechos Humanos emitió un oficio a mi despacho  solicitando que en mi calidad de asambleísta solicite videos y trazabilidad a Segura-EP  en relación a las bombas que explotaron en la bahía de Guayaquil. Lo hice de inmediato.  El 26 de septiembre del 25 solicité la información y el 29 de septiembre recibí la información.  Es por eso que el 15 de octubre los expuse. ¿Y digo por qué? Porque denunciamos que luego  de la explosión en la bahía de Guayaquil se detecta que Iván Ballesteros, supuesto implicado  en la explosión en la bahía, va a su domicilio, al siguiente día lo detienen y cinco minutos  después al domicilio del detenido del implicado Ballesteros. Cinco minutos después llega un  Porsche Cayenne de placas GRY 3452 perteneciente a Industrial Molinera, que pertenece a la familia  Novo. ¿Por qué no se investiga eso? Está claro. Ya está de dónde se obtuvo la información.  Y pregunto ante este pleno, ¿por qué han volcado todo el aparataje del Estado en contra  de quienes fiscalizamos? ¿Por qué? La sombra constante, la amenaza, la filtración de testimonios  manipulados en fiscalía. La fiscalía en relación a Ports dijo que no se puede abrir el teléfono  del señor Ballesteros porque no les ha entregado la clave. Pero lo más cínico de esta narrativa  es el falso discurso sobre los recursos públicos. Hoy se rascan las vestiduras diciendo que se han usado  dinero del Estado para investigar. ¡Qué ironía! Revisen por favor quién pagó el PIB en el último partido  de Ecuador. Aquí no hay ningún espionaje ilegal contra ciudadanos ni ciudadanas. Lo que hay es un  gobierno a que se le descubrieron sus pactos bajo la mesa y ahora quieren criminalizar a quienes hacemos  nuestro trabajo de fiscalización. Tremendo. Mientras el país se quedaba a oscuras y perdíamos millones  de dólares. No pasaba nada. Como no pasa nada con el caso Progen y ATM. Un robo descarado que nadie dice nada.  Como no pasa nada, como no pasa nada con el caso Porsche. Si yo no investigo, si yo no investigo el caso Porsche,  entonces después les suela que sí, el silencio tora. Que si no investigo la explosión de la bomba, que si no investigo  el carro Porsche Cayet que llega ahí. Entonces no me estoy convirtiendo en cómplice. Después les suele que supuesto autoatentado.  Y no pasa nada con los niños de las Malvinas. Después les suele supuesto terrorismo.  Y investiguen. Entonces, díganle al pueblo ecuatoriano qué pasa con 2.3 toneladas de cocaína en Blástica.  ¿Qué pasa con incautación de cocaína en San Luis? ¿Qué pasa con 70 millones de desvanecidos del SRI?  ¿Qué pasa con Gala Medios y la compra de medios de comunicación que nadie sabe cómo?  ¿Qué está pasando?  Pero, ¿saben lo que sucede aquí?  Hay ocasiones donde a mí me gustaría responder los insultos que se me generan.  Pero, como dijo Tsun Tzu, uno elige los enemigos y yo elijo mis enemigos.  Y para responder, tienen que estar a la altura del conflicto.  Así que, ¿saben qué es lo que pasa?  Es que como están acorralados, como no quieren investigar lo que realmente tienen que investigar,  es la vieja táctica de la impunidad.  Cuando descubren al corrupto robando porque una cámara lo grabó,  su defensa es acusar a quien instaló la cámara por invasión a la privacidad.  Y no pasa absolutamente nada.  Ecuatorianas y ecuatorianos.  Yo he sido realmente una persona que ha dado la cara ante el pueblo ecuatoriano.  Señores del gobierno, abran los teléfonos que quieran.  Expongan los audios que quieran.  Presionen a los testigos que quieran.  Inventen las historias que necesiten.  La verdad ya está afuera.  El caso Progen, el caso Porche, el caso Blastig, el Galamé, ya están afuera.  Y el pueblo conoce de aquello.  Y eso no se va a borrar de la mente del pueblo ecuatoriano  porque ustedes persigan a quienes estamos fiscalizando.  Sigan usando el aparataje del Estado como su escudo personal.  Que nosotros seguiremos usando la fiscalización desde aquí  y la fuerza del pueblo ecuatoriano  como nuestra única arma y herramienta  para defender este país  que ya se cansó de ustedes.  Buena suerte.",
      "speaker_id": "speaker_0",
      "speaker": {
        "id": "speaker_0",
        "name": "Juan Andrés González Alvear",
        "confidence": 0.75
      }
    }
  ],
  "video_id": "X3BAianQl_8",
  "source": "local-pyannote-community-1+whisper-large-v3-turbo",
  "speaker_mapping": {
    "speaker_0": {
      "name": "Juan Andrés González Alvear",
      "confidence": 0.75,
      "votes": {},
      "samples": 10,
      "successful_reads": 0,
      "source": "title"
    }
  },
  "title": "Asambleísta Juan González - Sesión 101",
  "url": "https://www.youtube.com/watch?v=X3BAianQl_8",
  "published_at": "2026-06-17T00:00:00Z",
  "channel_title": "Asamblea Nacional del Ecuador",
  "id": "X3BAianQl_8",
  "date": "2026-06-17T00:00:00Z",
  "source_url": "https://www.youtube.com/watch?v=X3BAianQl_8",
  "speaker_stats": [
    {
      "id": "speaker_0",
      "name": "Juan Andrés González Alvear",
      "party": null,
      "province": null,
      "total_time": 458.29,
      "interventions": 1,
      "word_count": 831
    }
  ],
  "video_type": "clip"
}