{
  "text": "Réplica la asambleísta Jairén Noriega.  Gracias, Presidenta. Pensé que no me iba a dar la palabra.  La legisladora Larcón, muy suelta de huesos, además,  nos decía que esta bancada, esta bancada que sí lee los proyectos de ley,  éramos expertos en votar en contra de leyes de seguridad.  Asambleísta Larcón.  Y lo que son expertos ustedes es en hacer la zapada,  porque en esta ley, en lugar de concentrarse en normar algo que evidentemente es necesario  como el control de uniformes y su uso y su comercialización,  ustedes lo que están haciendo a través del artículo 20 es blindando su corrupción.  Eso es lo que realmente quieren hacer a través de un proyecto de ley tan importante,  tan necesario y tan noble.  porque usted no podrá mentir que en la mesa legislativa,  tanto el colega Machado como yo, que somos parte de la mesa de seguridad,  nunca jamás nos opusimos a este proyecto de ley.  Nunca, señora Presidenta.  Pero de la noche a la mañana, y en medio de gallos, y media noche,  como les encanta y como acostumbran,  entonces aparece un artículo que nadie lo propuso, que nadie lo debatió,  que ningún experto ni siquiera tuvo la capacidad de pronunciarse,  porque mágicamente, insisto, apareció en el informe para segundo debate.  Y es un informe, es un artículo, colegas, para los que no leyeron,  porque yo estoy segura que les dijeron,  tiene que intervenir Pepito, Juanito y María.  Y entonces Pepito, Juanito y María dijeron,  sí, hay que proteger los uniformes de las Fuerzas Armadas y la Policía Nacional.  Por supuesto que sí hay que hacerlo.  Pero nadie leyó el artículo 20, y voy a proceder a hacerlo, señora Presidenta.  Dice lo siguiente.  ¿Saben qué información es clasificada como reservada, colegas?  Las declaraciones juradas de patrimonio.  Esas mismas gracias a las que el país se enteró, por ejemplo,  que uno de los suyos, uno de los legisladores de ADN alterno,  el señor Luis Alvarado Campi,  con un patrimonio declarado ante la Contraloría General del Estado,  solo tenía 66 mil dólares.  Pero, oh sorpresa, terminó comprando medios de comunicación  que hoy son serviles al gobierno por dos millones de dólares.  ¿De dónde salió la plata?  Esas respuestas son las que todavía ustedes, señores que se dan de dignos  y de protectores de la seguridad, todavía le deben al país.  Y sigo con el artículo.  Secreta o secretísima, relacionada con procesos, actuaciones, exámenes especiales,  auditorías o expedientes institucionales.  ¿Qué será que quieren eliminar?  Y ahí mi compañero Blasco me da la razón.  Progen.  Porque entonces, colegas, después de 30 días, tan solo 30 días de llegada a la información  a la Contraloría General del Estado,  la propia Contraloría tiene la posibilidad, a través de esta reforma,  de eliminar esta información.  Entonces, una vez más, no le traten a la gente de estúpida.  No le vengan a vender a la gente una reforma supuesta de seguridad,  cuando en último momento lo que ustedes hicieron fue meter un artículo para tapar su corrupción.  Y contra eso, por supuesto, por supuesto que votaremos que no.  Gracias, presidente.",
  "language": "es",
  "duration": 241.09,
  "speakers_detected": 1,
  "segments": [
    {
      "id": 0,
      "start": 0.03,
      "end": 241.06,
      "text": "Réplica la asambleísta Jairén Noriega.  Gracias, Presidenta. Pensé que no me iba a dar la palabra.  La legisladora Larcón, muy suelta de huesos, además,  nos decía que esta bancada, esta bancada que sí lee los proyectos de ley,  éramos expertos en votar en contra de leyes de seguridad.  Asambleísta Larcón.  Y lo que son expertos ustedes es en hacer la zapada,  porque en esta ley, en lugar de concentrarse en normar algo que evidentemente es necesario  como el control de uniformes y su uso y su comercialización,  ustedes lo que están haciendo a través del artículo 20 es blindando su corrupción.  Eso es lo que realmente quieren hacer a través de un proyecto de ley tan importante,  tan necesario y tan noble.  porque usted no podrá mentir que en la mesa legislativa,  tanto el colega Machado como yo, que somos parte de la mesa de seguridad,  nunca jamás nos opusimos a este proyecto de ley.  Nunca, señora Presidenta.  Pero de la noche a la mañana, y en medio de gallos, y media noche,  como les encanta y como acostumbran,  entonces aparece un artículo que nadie lo propuso, que nadie lo debatió,  que ningún experto ni siquiera tuvo la capacidad de pronunciarse,  porque mágicamente, insisto, apareció en el informe para segundo debate.  Y es un informe, es un artículo, colegas, para los que no leyeron,  porque yo estoy segura que les dijeron,  tiene que intervenir Pepito, Juanito y María.  Y entonces Pepito, Juanito y María dijeron,  sí, hay que proteger los uniformes de las Fuerzas Armadas y la Policía Nacional.  Por supuesto que sí hay que hacerlo.  Pero nadie leyó el artículo 20, y voy a proceder a hacerlo, señora Presidenta.  Dice lo siguiente.  ¿Saben qué información es clasificada como reservada, colegas?  Las declaraciones juradas de patrimonio.  Esas mismas gracias a las que el país se enteró, por ejemplo,  que uno de los suyos, uno de los legisladores de ADN alterno,  el señor Luis Alvarado Campi,  con un patrimonio declarado ante la Contraloría General del Estado,  solo tenía 66 mil dólares.  Pero, oh sorpresa, terminó comprando medios de comunicación  que hoy son serviles al gobierno por dos millones de dólares.  ¿De dónde salió la plata?  Esas respuestas son las que todavía ustedes, señores que se dan de dignos  y de protectores de la seguridad, todavía le deben al país.  Y sigo con el artículo.  Secreta o secretísima, relacionada con procesos, actuaciones, exámenes especiales,  auditorías o expedientes institucionales.  ¿Qué será que quieren eliminar?  Y ahí mi compañero Blasco me da la razón.  Progen.  Porque entonces, colegas, después de 30 días, tan solo 30 días de llegada a la información  a la Contraloría General del Estado,  la propia Contraloría tiene la posibilidad, a través de esta reforma,  de eliminar esta información.  Entonces, una vez más, no le traten a la gente de estúpida.  No le vengan a vender a la gente una reforma supuesta de seguridad,  cuando en último momento lo que ustedes hicieron fue meter un artículo para tapar su corrupción.  Y contra eso, por supuesto, por supuesto que votaremos que no.  Gracias, presidente.",
      "speaker_id": "speaker_0",
      "speaker": {
        "id": "speaker_0",
        "name": "Jahiren Elizabeth Noriega Donoso",
        "confidence": 1.0
      }
    }
  ],
  "video_id": "CUq8c-SBL3U",
  "source": "local-pyannote-community-1+whisper-large-v3-turbo",
  "speaker_mapping": {
    "speaker_0": {
      "name": "Jahiren Elizabeth Noriega Donoso",
      "confidence": 1.0,
      "votes": {
        "Jahiren Elizabeth Noriega Donoso": 7
      },
      "samples": 10,
      "successful_reads": 7,
      "source": "db"
    }
  },
  "title": "Asambleísta Jahiren Noriega - Sesión 099",
  "url": "https://www.youtube.com/watch?v=CUq8c-SBL3U",
  "published_at": "2026-06-09T00:00:00Z",
  "channel_title": "Asamblea Nacional del Ecuador",
  "id": "CUq8c-SBL3U",
  "date": "2026-06-09T00:00:00Z",
  "source_url": "https://www.youtube.com/watch?v=CUq8c-SBL3U",
  "speaker_stats": [
    {
      "id": "speaker_0",
      "name": "Jahiren Elizabeth Noriega Donoso",
      "party": null,
      "province": null,
      "total_time": 241.03,
      "interventions": 1,
      "word_count": 512
    }
  ]
}